VisionFive/__init__.py
VisionFive/_boardtype.cpython-310-riscv64-linux-gnu.so
VisionFive/_gpio.cpython-310-riscv64-linux-gnu.so
VisionFive/_i2c.cpython-310-riscv64-linux-gnu.so
VisionFive/_spi.cpython-310-riscv64-linux-gnu.so
VisionFive/boardtype/__init__.py
VisionFive/gpio/__init__.py
VisionFive/i2c/__init__.py
VisionFive/sample-code/I2C_Sense_Hat.py
VisionFive/sample-code/LED_Matrix.py
VisionFive/sample-code/RPi_demo_#GPIO_basic#_run_on_VisionFive.py
VisionFive/sample-code/RPi_demo_#PWM#_run_on_VisionFive.py
VisionFive/sample-code/__init__.py
VisionFive/sample-code/basic_edge_detection.py
VisionFive/sample-code/buzzer.py
VisionFive/sample-code/edge_detection_with_LED_Matrix.py
VisionFive/sample-code/edge_detection_with_waiting_time.py
VisionFive/sample-code/led.py
VisionFive/sample-code/pud_test.py
VisionFive/sample-code/pwm_led.py
VisionFive/sample-code/uart_gps_demo.py
VisionFive/sample-code/lcddemo/__init__.py
VisionFive/sample-code/lcddemo/example/2.4inch_LCD_demo.py
VisionFive/sample-code/lcddemo/example/LCD_2inch.jpg
VisionFive/sample-code/lcddemo/example/LCD_2inch4_parrot.bmp
VisionFive/sample-code/lcddemo/example/__init__.py
VisionFive/sample-code/lcddemo/example/visionfive.bmp
VisionFive/sample-code/lcddemo/example/visionfive2.png
VisionFive/sample-code/lcddemo/lib/LCD2inch4_lib.py
VisionFive/sample-code/lcddemo/lib/__init__.py
VisionFive/spi/__init__.py
visionfive_gpio-1.3.3.dist-info/licenses/LICENCE.txt
visionfive_gpio-1.3.3.dist-info/METADATA
visionfive_gpio-1.3.3.dist-info/WHEEL
visionfive_gpio-1.3.3.dist-info/top_level.txt
visionfive_gpio-1.3.3.dist-info/RECORD
