Metadata-Version: 2.4
Name: VisionFive.gpio
Version: 1.3.3
Summary: A module to control VisionFive GPIO ports
Home-page: http://gitlab.starfivetech.com/product1/software-ae/visionfive-python-gpio/gpio-libs
Author: StarFive
Author-email: support@starfivetech.com
License: MIT
Keywords: VisionFive GPIO
Classifier: Development Status :: 5 - Production/Stable
Classifier: Operating System :: POSIX :: Linux
Classifier: License :: OSI Approved :: MIT License
Classifier: Intended Audience :: Developers
Classifier: Programming Language :: Python :: 3
Classifier: Programming Language :: Python :: 3.10
Classifier: Programming Language :: Python :: 3.11
Classifier: Programming Language :: Python :: 3.12
Classifier: Topic :: Software Development
Classifier: Topic :: Home Automation
Classifier: Topic :: System :: Hardware
License-File: LICENCE.txt
Dynamic: author
Dynamic: author-email
Dynamic: classifier
Dynamic: description
Dynamic: home-page
Dynamic: keywords
Dynamic: license
Dynamic: license-file
Dynamic: summary
